taskmanager_pakas342/main.py
taskmanager_pakas342/task_maker_brain.py
taskmanager_pakas342-0.1.1.dist-info/METADATA
taskmanager_pakas342-0.1.1.dist-info/WHEEL
taskmanager_pakas342-0.1.1.dist-info/entry_points.txt
taskmanager_pakas342-0.1.1.dist-info/RECORD
