Metadata-Version: 2.3
Name: taskmanager_pakas342
Version: 0.1.1
Summary: Simple task manager
Requires-Python: >=3.7
